test_package_1/__init__.py
test_package_1/module_dummy.py
alfredo_test_package_1-0.1.0.dist-info/METADATA
alfredo_test_package_1-0.1.0.dist-info/WHEEL
alfredo_test_package_1-0.1.0.dist-info/RECORD
