Metadata-Version: 2.4
Name: alfredo_test_package_1
Version: 0.1.0
Summary: Dummy project 1
Author-email: Alfredo Cinelli <alfredocinelli96@gmail.com>
License-Expression: MIT
Classifier: Development Status :: 3 - Alpha
Classifier: Intended Audience :: Developers
Classifier: License :: OSI Approved :: MIT License
Classifier: Natural Language :: English
Classifier: Operating System :: OS Independent
Classifier: Programming Language :: Python :: 3.12
Classifier: Topic :: Software Development :: Libraries :: Python Modules
Requires-Python: >=3.12
